README.md
setup.py
apistar/__init__.py
apistar/cli.py
apistar/compat.py
apistar/core.py
apistar/document.py
apistar/exceptions.py
apistar/formats.py
apistar/types.py
apistar/validators.py
apistar.egg-info/PKG-INFO
apistar.egg-info/SOURCES.txt
apistar.egg-info/dependency_links.txt
apistar.egg-info/entry_points.txt
apistar.egg-info/requires.txt
apistar.egg-info/top_level.txt
apistar/client/__init__.py
apistar/client/auth.py
apistar/client/client.py
apistar/client/debug.py
apistar/client/decoders.py
apistar/client/encoders.py
apistar/client/transports.py
apistar/schemas/__init__.py
apistar/schemas/config.py
apistar/schemas/jsonschema.py
apistar/schemas/openapi.py
apistar/schemas/swagger.py
apistar/themes/apistar/static/css/base.css
apistar/themes/apistar/static/css/bootstrap.min.css
apistar/themes/apistar/static/css/font-awesome-4.0.3.css
apistar/themes/apistar/static/fonts/fontawesome-webfont.eot
apistar/themes/apistar/static/fonts/fontawesome-webfont.svg
apistar/themes/apistar/static/fonts/fontawesome-webfont.ttf
apistar/themes/apistar/static/fonts/fontawesome-webfont.woff
apistar/themes/apistar/static/img/favicon.ico
apistar/themes/apistar/static/img/grid.png
apistar/themes/apistar/static/img/gripper.png
apistar/themes/apistar/static/img/logomarque-small-white.png
apistar/themes/apistar/static/js/api.js
apistar/themes/apistar/static/js/bootstrap.min.js
apistar/themes/apistar/static/js/jquery-1.10.2.min.js
apistar/themes/apistar/templates/index.html
apistar/themes/apistar/templates/langs/javascript.html
apistar/themes/apistar/templates/langs/python.html
apistar/themes/apistar/templates/layout/content.html
apistar/themes/apistar/templates/layout/link.html
apistar/themes/apistar/templates/layout/sidebar.html
apistar/themes/redoc/LICENSE.md
apistar/themes/redoc/static/js/redoc.standalone.js
apistar/themes/redoc/templates/index.html
apistar/themes/swaggerui/LICENSE.md
apistar/themes/swaggerui/static/css/swagger-ui.css
apistar/themes/swaggerui/static/css/swagger-ui.css.map
apistar/themes/swaggerui/static/js/swagger-ui-bundle.js
apistar/themes/swaggerui/static/js/swagger-ui-bundle.js.map
apistar/themes/swaggerui/static/js/swagger-ui-standalone-preset.js
